<DOMDocument xmlns:xsi="http://www.w3.org/2001/XMLSchema-instance" xmlns="http://ns.adobe.com/xfl/2008/" width="1280" height="720" frameRate="60" currentTimeline="1" xflVersion="2.2" creatorInfo="Adobe Flash Professional CS6" platform="Macintosh" versionInfo="Saved by Adobe Flash Macintosh 12.0 build 537" majorVersion="12" buildNumber="537" viewAngle3D="100.925968316201" nextSceneIdentifier="2" playOptionsPlayLoop="false" playOptionsPlayPages="false" playOptionsPlayFrameActions="false" autoSaveEnabled="true" autoSaveHasPrompted="true">
     <media>
          <DOMBitmapItem name="Vignette.png" itemID="5294b857-000002af" sourceExternalFilepath="/Users/shunghsiyu/Documents/Flash Projects/TheCycleProgram/TheCycle/LIBRARY/Vignette.png" sourceLastImported="1385478231" sourcePlatform="macintosh" externalFileCRC32="4101121944" externalFileSize="247552" allowSmoothing="true" useImportedJPEGData="false" compressionType="lossless" originalCompressionType="lossless" quality="50" href="Vignette.png" bitmapDataHRef="M 1 1384488086.dat" frameRight="49600" frameBottom="37680"/>
     </media>
     <symbols>
          <Include href="ChemLabel.xml" itemID="5283f1aa-000004fd" lastModified="1384475356"/>
          <Include href="Cycle.xml" itemID="52770114-00000524" lastModified="1385414806"/>
          <Include href="CycleGroup.xml" itemID="5294b89d-000002b1" lastModified="1385478301"/>
          <Include href="Vignette.xml" loadImmediate="false" itemID="5294b838-000002ac" lastModified="1385478200"/>
     </symbols>
     <timelines>
          <DOMTimeline name="Scene 1">
               <layers>
                    <DOMLayer name="Layer 1" color="#4FFF4F" current="true" isSelected="true">
                         <frames>
                              <DOMFrame index="0" keyMode="9728">
                                   <elements>
                                        <DOMSymbolInstance libraryItemName="Vignette" name="cycleGroup" centerPoint3DX="640.15" centerPoint3DY="360.05">
                                             <matrix>
                                                  <Matrix tx="-599.85" ty="-205.1"/>
                                             </matrix>
                                             <transformationPoint>
                                                  <Point x="1240" y="565.15"/>
                                             </transformationPoint>
                                             <color>
                                                  <Color alphaMultiplier="0.69140625"/>
                                             </color>
                                        </DOMSymbolInstance>
                                        <DOMSymbolInstance libraryItemName="CycleGroup" name="cycleGroup" selected="true">
                                             <transformationPoint>
                                                  <Point/>
                                             </transformationPoint>
                                        </DOMSymbolInstance>
                                   </elements>
                              </DOMFrame>
                         </frames>
                    </DOMLayer>
               </layers>
          </DOMTimeline>
     </timelines>
     <persistentData>
          <PD n="CreateJSToolkit_data" v="version&#xA;0.1&#xA;libraryPath&#xA;libs/&#xA;createjsNS&#xA;createjs&#xA;exportHTML&#xA;true&#xA;frameBounds&#xA;false&#xA;includeHiddenLayers&#xA;true&#xA;preview&#xA;true&#xA;imagesPath&#xA;images/&#xA;soundsPath&#xA;sounds/&#xA;compactPaths&#xA;true&#xA;imagesNS&#xA;images&#xA;exportSounds&#xA;true&#xA;exportLibs&#xA;true&#xA;exportImages&#xA;true&#xA;hostedLibs&#xA;true&#xA;outputPath&#xA;./CreatJS/&#xA;libNS&#xA;lib"/>
          <PD n="CreateJSToolkit_timelinedata" v="version&#xA;0.1&#xA;loop&#xA;false"/>
     </persistentData>
     <PrinterSettings platform="macintosh"/>
     <publishHistory>
          <PublishItem publishSize="222605" publishTime="1385478721" publishDebug="true"/>
          <PublishItem publishSize="222219" publishTime="1385478370" publishDebug="true"/>
          <PublishItem publishSize="222171" publishTime="1385478360" publishDebug="true"/>
          <PublishItem publishSize="222158" publishTime="1385478337" publishDebug="true"/>
          <PublishItem publishSize="222097" publishTime="1385419917" publishDebug="true"/>
          <PublishItem publishSize="222111" publishTime="1385419859" publishDebug="true"/>
          <PublishItem publishSize="222111" publishTime="1385419783" publishDebug="true"/>
          <PublishItem publishSize="222104" publishTime="1385419701" publishDebug="true"/>
          <PublishItem publishSize="222115" publishTime="1385419664" publishDebug="true"/>
          <PublishItem publishSize="222124" publishTime="1385419642" publishDebug="true"/>
          <PublishItem publishSize="222136" publishTime="1385419618" publishDebug="true"/>
          <PublishItem publishSize="222141" publishTime="1385419605" publishDebug="true"/>
          <PublishItem publishSize="222069" publishTime="1385419467" publishDebug="true"/>
          <PublishItem publishSize="222065" publishTime="1385419383" publishDebug="true"/>
          <PublishItem publishSize="222098" publishTime="1385419117" publishDebug="true"/>
          <PublishItem publishSize="222062" publishTime="1385419055" publishDebug="true"/>
          <PublishItem publishSize="222067" publishTime="1385419026" publishDebug="true"/>
          <PublishItem publishSize="222070" publishTime="1385418974" publishDebug="true"/>
          <PublishItem publishSize="222063" publishTime="1385418938" publishDebug="true"/>
          <PublishItem publishSize="221815" publishTime="1385418330" publishDebug="true"/>
     </publishHistory>
</DOMDocument>